vk_cities/models.py
vk_cities/apps.py
vk_cities/utils.py
vk_cities/__init__.py
vk_cities/admin.py
vk_cities/migrations/__init__.py
vk_cities/migrations/0001_initial.py
vk_cities/management/__init__.py
vk_cities/management/commands/__init__.py
vk_cities/management/commands/vk_cities.py
django_vk_cities-1.0.1.dist-info/top_level.txt
django_vk_cities-1.0.1.dist-info/WHEEL
django_vk_cities-1.0.1.dist-info/METADATA
django_vk_cities-1.0.1.dist-info/RECORD
django_vk_cities-1.0.1.dist-info/metadata.json
django_vk_cities-1.0.1.dist-info/DESCRIPTION.rst
example/urls.py
example/__init__.py
example/manage.py
example/settings.py
