Metadata-Version: 2.0
Name: django-vk-cities
Version: 1.0.1
Summary: Django package for using VK.com cities database
Home-page: https://github.com/pyvim/django-vk-cities
Author: Vitalii Maslov
Author-email: me@pyvim.com
License: MIT
Download-URL: https://github.com/pyvim/django-vk-cities/tarball/master
Keywords: django,vk,cities,places
Platform: UNKNOWN
Classifier: Environment :: Web Environment
Classifier: Intended Audience :: Developers
Classifier: Programming Language :: Python
Requires-Dist: vklancer
